rigidipy/__init__.py
rigidipy/rigidipy.py
rigidipy/bin/__init__.py
rigidipy/bin/calc_rigidity_OSX.bin
rigidipy/bin/calc_rigidity_gcc4.8.4.bin
rigidipy/bin/lib/__init__.py
rigidipy/bin/lib/distance_cutoffs.txt
rigidipy/bin/lib/het_dictionary.txt
rigidipy/bin/lib/std_dictionary.txt
rigidipy-0.0.1.dist-info/LICENSE
rigidipy-0.0.1.dist-info/METADATA
rigidipy-0.0.1.dist-info/WHEEL
rigidipy-0.0.1.dist-info/entry_points.txt
rigidipy-0.0.1.dist-info/top_level.txt
rigidipy-0.0.1.dist-info/RECORD
