Metadata-Version: 2.1
Name: rigidipy
Version: 0.0.1
Summary: Compute protein flexibility from chemical shifts in NEF format.
Home-page: https://github.com/nickjf/rigidipy
Author: Nick J Fowler
Author-email: nickjfowler0@gmail.com
License: UNKNOWN
Project-URL: Bug Tracker, https://github.com/nickjf/rigidipy/issues
Platform: UNKNOWN
Classifier: Programming Language :: Python :: 3
Classifier: License :: OSI Approved :: MIT License
Classifier: Operating System :: OS Independent
Requires-Python: >=3.6
License-File: LICENSE
Requires-Dist: numpy
